devopsnextgenx/__init__.py
devopsnextgenx/components/Carousel.py
devopsnextgenx/components/ProgressPopup.py
devopsnextgenx/components/ScrollFrame.py
devopsnextgenx/components/StatusBar.py
devopsnextgenx/components/Table.py
devopsnextgenx/components/__init__.py
devopsnextgenx/components/messageHub/Alert.py
devopsnextgenx/components/messageHub/Banner.py
devopsnextgenx/components/messageHub/Notification.py
devopsnextgenx/components/messageHub/__init__.py
devopsnextgenx/components/messageHub/provider.py
devopsnextgenx/utils/__init__.py
devopsnextgenx/utils/guiUtils.py
devopsnextgenx/utils/iconProvider.py
devopsnextgenx/utils/style.py
devopsnextgenx/utils/windowPosition.py
ctk_gui_components-0.2.3.dist-info/METADATA
ctk_gui_components-0.2.3.dist-info/WHEEL
ctk_gui_components-0.2.3.dist-info/top_level.txt
ctk_gui_components-0.2.3.dist-info/RECORD
