Metadata-Version: 2.1
Name: ctk-gui-components
Version: 0.2.3
Summary: A collection of custom GUI components for Python
Home-page: https://github.com/devopsnextgenx/ctk-gui-components
Author: Amit Kshirsagar
Author-email: devopsnextgenx@gmail.com
License: SLA
Classifier: Programming Language :: Python :: 3
Classifier: Operating System :: OS Independent
Classifier: License :: Other/Proprietary License
Requires-Python: >=3.8
Requires-Dist: customtkinter
Requires-Dist: ttkbootstrap
